{
	"schema":
	{
		"examiner":"Tugbeh Emmanuel",
		"course":"APEX Software Test",	
		"total":"5",
		"time":"5",
		"date":"2011-11-14"
	},
	"table":
	[
		{
			"question":"What is ConRAD LTE?",
			"option1":"Examination Portal",
			"option2":"Examination Software",
			"option3":"Content Management System",
			"option4":"Database Application",
			"answer":"option4"
		},
		{
			"question":"ConRAD LTE is owned and developed by __________?",
			"option1":"Adobe Systems",
			"option2":"GitHub Inc.",
			"option3":"HWP Labs",
			"option4":"NIIT",
			"answer":"option3"
		},
		{
			"question":"Who is the Founder/CEO of ConRAD LTE?",
			"option1":"Chris Wanstrath",
			"option2":"Tugbeh Emmanuel",
			"option3":"Sapnesh Lalla",
			"option4":"Shantanu Narayen",
			"answer":"option2"
		},
		{
			"question":"What is the brand color of ConRAD LTE?",
			"option1":"Blue",
			"option2":"Red",
			"option3":"Green",
			"option4":"Yellow",
			"answer":"option1"
		},
		{
			"question":"ConRAD LTE server-side scripting was written in __________?",
			"option1":"PHP",
			"option2":"ASP",
			"option3":"Node.js",
			"option4":"JSP",
			"answer":"option1"
		}		
	]
}
